service_buddy_too/__init__.py
service_buddy_too/commandline.py
service_buddy_too/ci/__init__.py
service_buddy_too/ci/bamboo_build_creator.py
service_buddy_too/ci/bitbucket_pipeline_build_creator.py
service_buddy_too/ci/build_creator.py
service_buddy_too/ci/ci.py
service_buddy_too/ci/travis_build_creator.py
service_buddy_too/codegenerator/__init__.py
service_buddy_too/codegenerator/builtin-code-templates.json
service_buddy_too/codegenerator/code_creator.py
service_buddy_too/codegenerator/cookie_cutter_creator.py
service_buddy_too/commands/__init__.py
service_buddy_too/commands/bootstrap/__init__.py
service_buddy_too/commands/bootstrap/command.py
service_buddy_too/commands/clone/__init__.py
service_buddy_too/commands/clone/command.py
service_buddy_too/commands/git/__init__.py
service_buddy_too/commands/git/command.py
service_buddy_too/commands/initialize/__init__.py
service_buddy_too/commands/initialize/command.py
service_buddy_too/commands/list/__init__.py
service_buddy_too/commands/list/command.py
service_buddy_too/context/__init__.py
service_buddy_too/context/service_context.py
service_buddy_too/service/__init__.py
service_buddy_too/service/application.py
service_buddy_too/service/initializer.py
service_buddy_too/service/loader.py
service_buddy_too/service/service.py
service_buddy_too/service/service_template_generator.py
service_buddy_too/util/__init__.py
service_buddy_too/util/command_util.py
service_buddy_too/util/log_handler.py
service_buddy_too/util/pretty_printer.py
service_buddy_too/vcs/__init__.py
service_buddy_too/vcs/bitbucket.py
service_buddy_too/vcs/github_vcs.py
service_buddy_too/vcs/vcs.py
service_buddy_too-0.1.61.data/scripts/service-buddy
service_buddy_too-0.1.61.dist-info/LICENSE
service_buddy_too-0.1.61.dist-info/METADATA
service_buddy_too-0.1.61.dist-info/WHEEL
service_buddy_too-0.1.61.dist-info/namespace_packages.txt
service_buddy_too-0.1.61.dist-info/top_level.txt
service_buddy_too-0.1.61.dist-info/zip-safe
service_buddy_too-0.1.61.dist-info/RECORD
