Metadata-Version: 2.1
Name: service-buddy-too
Version: 0.1.61
Summary: CLI for managing micro-services
Home-page: https://github.com/rspitler/service-buddy
Author: 
Author-email: 
Maintainer: 
Maintainer-email: 
License: Apache 2.0
Classifier: Development Status :: 3 - Alpha
Classifier: Programming Language :: Python
License-File: LICENSE
Requires-Dist: PyGithub
Requires-Dist: cookiecutter ==2.1.1
Requires-Dist: click
Requires-Dist: infra-buddy-too
Requires-Dist: requests
Requires-Dist: atlassian-python-api
